{"type": "FeatureCollection", "name": "dispatch_walk_log", "features": [{"type": "Feature", "properties": {"Zone_ID": "Dispatch"}, "geometry": {"type": "Point", "coordinates": [-73.95003953, 40.85578134]}}], "crs": {"type": "name", "properties": {"name": "urn:ogc:def:crs:OGC:1.3:CRS84"}}}