{"type": "FeatureCollection", "name": "dispatch_walk_log", "features": [{"type": "Feature", "properties": {"Zone_ID": "Dispatch", "1/19/26 AM": 2, "1/19/26 PM": 2, "1/26/26 AM": 2, "1/26/26 PM": 0, "2/2/26 AM": 1, "2/2/26 PM": 1, "2/9/26 AM": 1, "2/9/26 PM": 1, "2/16/26 AM": 0, "2/16/26 PM": 2, "2/23/26 AM": 3, "2/23/26 PM": 2, "Avg AM": 1.5, "Avg PM": 1.3}, "geometry": {"type": "Point", "coordinates": [-73.95003953, 40.85578134]}}], "crs": {"type": "name", "properties": {"name": "urn:ogc:def:crs:OGC:1.3:CRS84"}}}